[{"authors":["admin"],"categories":null,"content":"I am a Senior Data Scientist at idealista/data. Previously, I worked as an Applied Economics researcher in different projects at University of Oviedo. During three of those years my main focus was to write a Ph.D. on Transportation Economics, Spatial Econometrics and Regional Science. In 2015 I left Academia for pursuing a career in Data Science. Firstly, I worked for a small startup in the Telecommunications sector and then moved to a consutancy firm where I succesfully developed a Recommender System for a large retail company. Currently I work for idealista, the leading real estate portal in Southern Europe.\n","date":-62135596800,"expirydate":-62135596800,"kind":"taxonomy","lang":"en","lastmod":-62135596800,"objectID":"2525497d367e79493fd32b198b28f040","permalink":"http://pelayoarbues.github.io/authors/admin/","publishdate":"0001-01-01T00:00:00Z","relpermalink":"/authors/admin/","section":"authors","summary":"I am a Senior Data Scientist at idealista/data. Previously, I worked as an Applied Economics researcher in different projects at University of Oviedo. During three of those years my main focus was to write a Ph.D. on Transportation Economics, Spatial Econometrics and Regional Science. In 2015 I left Academia for pursuing a career in Data Science. Firstly, I worked for a small startup in the Telecommunications sector and then moved to a consutancy firm where I succesfully developed a Recommender System for a large retail company.","tags":null,"title":"Pelayo Arbués","type":"authors"},{"authors":[],"categories":null,"content":"","date":1568916000,"expirydate":-62135596800,"kind":"page","lang":"en","lastmod":1568916000,"objectID":"bb8f85ae025aea5ec7b017f42731a966","permalink":"http://pelayoarbues.github.io/talk/databeers-xxx/","publishdate":"2020-02-02T15:32:38+01:00","relpermalink":"/talk/databeers-xxx/","section":"talk","summary":"My talk \"Busco Pisco\" for Databeers XXX.","tags":[],"title":"Databeers XXX","type":"talk"}]